{
  "name": "Mount Warning Summit Trail",
  "region": "Northern Rivers, NSW",
  "country": "AU",
  "officialDistanceKm": 9,
  "typicalDays": "1",
  "coordinates": [
    [
      153.284597,
      -28.398288,
      432
    ],
    [
      153.284555,
      -28.398379,
      436
    ],
    [
      153.284487,
      -28.398449,
      439
    ],
    [
      153.284395,
      -28.398488,
      442
    ],
    [
      153.284301,
      -28.398537,
      444
    ],
    [
      153.284241,
      -28.398616,
      446
    ],
    [
      153.28414,
      -28.39858,
      446
    ],
    [
      153.284083,
      -28.398475,
      445
    ],
    [
      153.284039,
      -28.398388,
      445
    ],
    [
      153.28415,
      -28.398698,
      448
    ],
    [
      153.284187,
      -28.398793,
      451
    ],
    [
      153.284224,
      -28.398883,
      453
    ],
    [
      153.28415,
      -28.398617,
      446
    ],
    [
      153.284209,
      -28.398525,
      444
    ],
    [
      153.284241,
      -28.398611,
      446
    ],
    [
      153.284187,
      -28.398696,
      448
    ],
    [
      153.28414,
      -28.398777,
      450
    ],
    [
      153.284095,
      -28.398868,
      452
    ],
    [
      153.284175,
      -28.398935,
      454
    ],
    [
      153.284268,
      -28.39898,
      456
    ],
    [
      153.28437,
      -28.398982,
      456
    ],
    [
      153.284391,
      -28.39908,
      459
    ],
    [
      153.284324,
      -28.39918,
      462
    ],
    [
      153.284423,
      -28.399255,
      465
    ],
    [
      153.284378,
      -28.399345,
      468
    ],
    [
      153.284289,
      -28.399413,
      471
    ],
    [
      153.284209,
      -28.399481,
      475
    ],
    [
      153.2841,
      -28.399518,
      477
    ],
    [
      153.284001,
      -28.399546,
      478
    ],
    [
      153.283911,
      -28.399588,
      480
    ],
    [
      153.283814,
      -28.399637,
      480
    ],
    [
      153.283717,
      -28.399681,
      480
    ],
    [
      153.283615,
      -28.399692,
      479
    ],
    [
      153.283522,
      -28.399739,
      480
    ],
    [
      153.283427,
      -28.399775,
      480
    ],
    [
      153.283318,
      -28.399755,
      479
    ],
    [
      153.283216,
      -28.399789,
      479
    ],
    [
      153.283183,
      -28.399884,
      481
    ],
    [
      153.283153,
      -28.399973,
      483
    ],
    [
      153.283078,
      -28.400042,
      485
    ],
    [
      153.282996,
      -28.40012,
      488
    ],
    [
      153.282921,
      -28.400182,
      489
    ],
    [
      153.282808,
      -28.400187,
      490
    ],
    [
      153.28269,
      -28.400185,
      490
    ],
    [
      153.282594,
      -28.40024,
      492
    ],
    [
      153.282493,
      -28.400253,
      494
    ],
    [
      153.282423,
      -28.400326,
      498
    ],
    [
      153.282373,
      -28.400412,
      503
    ],
    [
      153.282321,
      -28.400502,
      508
    ],
    [
      153.282315,
      -28.400596,
      513
    ],
    [
      153.282283,
      -28.400684,
      519
    ],
    [
      153.28227,
      -28.400786,
      525
    ],
    [
      153.282212,
      -28.400872,
      530
    ],
    [
      153.282117,
      -28.400929,
      533
    ],
    [
      153.282012,
      -28.400957,
      535
    ],
    [
      153.281937,
      -28.400893,
      531
    ],
    [
      153.281828,
      -28.400855,
      529
    ],
    [
      153.281722,
      -28.400841,
      529
    ],
    [
      153.281613,
      -28.400837,
      530
    ],
    [
      153.281512,
      -28.400884,
      533
    ],
    [
      153.281409,
      -28.400904,
      535
    ],
    [
      153.281341,
      -28.400974,
      540
    ],
    [
      153.281332,
      -28.401065,
      544
    ],
    [
      153.281298,
      -28.401158,
      548
    ],
    [
      153.281271,
      -28.401247,
      551
    ],
    [
      153.2812,
      -28.401317,
      553
    ],
    [
      153.281121,
      -28.401374,
      555
    ],
    [
      153.281055,
      -28.401448,
      557
    ],
    [
      153.280995,
      -28.401524,
      558
    ],
    [
      153.280937,
      -28.401618,
      561
    ],
    [
      153.280885,
      -28.401707,
      564
    ],
    [
      153.280901,
      -28.401802,
      568
    ],
    [
      153.280801,
      -28.401778,
      567
    ],
    [
      153.280695,
      -28.401785,
      568
    ],
    [
      153.280608,
      -28.401731,
      567
    ],
    [
      153.280527,
      -28.401648,
      566
    ],
    [
      153.280606,
      -28.401587,
      562
    ],
    [
      153.280552,
      -28.401509,
      560
    ],
    [
      153.280472,
      -28.401451,
      560
    ],
    [
      153.280408,
      -28.401372,
      559
    ],
    [
      153.280318,
      -28.401304,
      560
    ],
    [
      153.280291,
      -28.401216,
      558
    ],
    [
      153.280189,
      -28.401174,
      558
    ],
    [
      153.280096,
      -28.401137,
      559
    ],
    [
      153.279985,
      -28.401158,
      561
    ],
    [
      153.279876,
      -28.401204,
      565
    ],
    [
      153.279768,
      -28.401236,
      568
    ],
    [
      153.279665,
      -28.401204,
      570
    ],
    [
      153.279552,
      -28.401198,
      573
    ],
    [
      153.279432,
      -28.401182,
      577
    ],
    [
      153.279329,
      -28.401149,
      581
    ],
    [
      153.279216,
      -28.401133,
      585
    ],
    [
      153.279116,
      -28.401057,
      587
    ],
    [
      153.279034,
      -28.401002,
      588
    ],
    [
      153.27892,
      -28.400981,
      593
    ],
    [
      153.278822,
      -28.4009,
      594
    ],
    [
      153.278792,
      -28.4008,
      591
    ],
    [
      153.278726,
      -28.400714,
      591
    ],
    [
      153.278702,
      -28.400619,
      588
    ],
    [
      153.278642,
      -28.400535,
      588
    ],
    [
      153.278638,
      -28.400635,
      592
    ],
    [
      153.278608,
      -28.40073,
      597
    ],
    [
      153.278596,
      -28.400839,
      602
    ],
    [
      153.27856,
      -28.400932,
      605
    ],
    [
      153.278644,
      -28.400992,
      604
    ],
    [
      153.278724,
      -28.401065,
      604
    ],
    [
      153.278734,
      -28.401172,
      606
    ],
    [
      153.278759,
      -28.40126,
      607
    ],
    [
      153.27875,
      -28.401352,
      609
    ],
    [
      153.27876,
      -28.401445,
      610
    ],
    [
      153.278838,
      -28.401516,
      609
    ],
    [
      153.278903,
      -28.401596,
      609
    ],
    [
      153.278966,
      -28.401674,
      608
    ],
    [
      153.278899,
      -28.401769,
      610
    ],
    [
      153.27879,
      -28.40181,
      612
    ],
    [
      153.278777,
      -28.401911,
      612
    ],
    [
      153.278728,
      -28.401816,
      612
    ],
    [
      153.278634,
      -28.401743,
      613
    ],
    [
      153.278544,
      -28.401697,
      615
    ],
    [
      153.278447,
      -28.401634,
      616
    ],
    [
      153.278366,
      -28.401575,
      618
    ],
    [
      153.278317,
      -28.401487,
      619
    ],
    [
      153.278262,
      -28.401389,
      621
    ],
    [
      153.278193,
      -28.401322,
      624
    ],
    [
      153.278097,
      -28.40126,
      628
    ],
    [
      153.278017,
      -28.401185,
      631
    ],
    [
      153.277903,
      -28.401183,
      637
    ],
    [
      153.277786,
      -28.401153,
      643
    ],
    [
      153.27771,
      -28.401061,
      646
    ],
    [
      153.277731,
      -28.400954,
      645
    ],
    [
      153.27776,
      -28.400856,
      644
    ],
    [
      153.277795,
      -28.400758,
      641
    ],
    [
      153.277816,
      -28.400664,
      639
    ],
    [
      153.277748,
      -28.400593,
      643
    ],
    [
      153.27768,
      -28.400524,
      646
    ],
    [
      153.277631,
      -28.400441,
      647
    ],
    [
      153.277571,
      -28.400528,
      652
    ],
    [
      153.27758,
      -28.400628,
      652
    ],
    [
      153.277592,
      -28.400727,
      652
    ],
    [
      153.27757,
      -28.400829,
      654
    ],
    [
      153.277507,
      -28.400901,
      657
    ],
    [
      153.277431,
      -28.400975,
      660
    ],
    [
      153.277352,
      -28.401039,
      662
    ],
    [
      153.277265,
      -28.401116,
      664
    ],
    [
      153.277211,
      -28.401202,
      664
    ],
    [
      153.277146,
      -28.401272,
      665
    ],
    [
      153.277061,
      -28.401322,
      666
    ],
    [
      153.277014,
      -28.40141,
      665
    ],
    [
      153.276943,
      -28.401488,
      663
    ],
    [
      153.276832,
      -28.401513,
      665
    ],
    [
      153.27672,
      -28.401578,
      666
    ],
    [
      153.276626,
      -28.401623,
      667
    ],
    [
      153.27659,
      -28.40172,
      665
    ],
    [
      153.276484,
      -28.401735,
      670
    ],
    [
      153.276418,
      -28.401813,
      670
    ],
    [
      153.27631,
      -28.401794,
      676
    ],
    [
      153.276197,
      -28.401778,
      682
    ],
    [
      153.276098,
      -28.401812,
      685
    ],
    [
      153.276049,
      -28.401912,
      683
    ],
    [
      153.275995,
      -28.401991,
      682
    ],
    [
      153.275901,
      -28.402029,
      684
    ],
    [
      153.275791,
      -28.402043,
      689
    ],
    [
      153.27573,
      -28.401956,
      696
    ],
    [
      153.275796,
      -28.401873,
      696
    ],
    [
      153.275853,
      -28.401794,
      696
    ],
    [
      153.275925,
      -28.401713,
      696
    ],
    [
      153.275972,
      -28.40163,
      697
    ],
    [
      153.276048,
      -28.401564,
      696
    ],
    [
      153.276055,
      -28.40147,
      698
    ],
    [
      153.276046,
      -28.401379,
      701
    ],
    [
      153.27611,
      -28.401307,
      700
    ],
    [
      153.276154,
      -28.401225,
      701
    ],
    [
      153.276154,
      -28.401121,
      704
    ],
    [
      153.276119,
      -28.401028,
      708
    ],
    [
      153.276068,
      -28.400926,
      714
    ],
    [
      153.276137,
      -28.400845,
      714
    ],
    [
      153.276175,
      -28.400751,
      714
    ],
    [
      153.276204,
      -28.400658,
      715
    ],
    [
      153.276196,
      -28.40056,
      717
    ],
    [
      153.276139,
      -28.400472,
      720
    ],
    [
      153.276141,
      -28.400374,
      721
    ],
    [
      153.276124,
      -28.400471,
      720
    ],
    [
      153.276042,
      -28.400559,
      724
    ],
    [
      153.275995,
      -28.400653,
      724
    ],
    [
      153.275888,
      -28.400681,
      729
    ],
    [
      153.275838,
      -28.400765,
      729
    ],
    [
      153.27586,
      -28.400865,
      725
    ],
    [
      153.275746,
      -28.400873,
      730
    ],
    [
      153.27566,
      -28.40093,
      733
    ],
    [
      153.275562,
      -28.40097,
      736
    ],
    [
      153.275482,
      -28.401033,
      737
    ],
    [
      153.275388,
      -28.401095,
      740
    ],
    [
      153.275402,
      -28.400995,
      743
    ],
    [
      153.275448,
      -28.400909,
      743
    ],
    [
      153.275472,
      -28.400811,
      746
    ],
    [
      153.275514,
      -28.40071,
      747
    ],
    [
      153.27557,
      -28.400616,
      747
    ],
    [
      153.275597,
      -28.40052,
      748
    ],
    [
      153.275657,
      -28.40044,
      746
    ],
    [
      153.275566,
      -28.400501,
      750
    ],
    [
      153.275487,
      -28.400564,
      752
    ],
    [
      153.275387,
      -28.400588,
      755
    ],
    [
      153.275313,
      -28.400652,
      757
    ],
    [
      153.275216,
      -28.400683,
      761
    ],
    [
      153.275118,
      -28.400733,
      766
    ],
    [
      153.275052,
      -28.400809,
      768
    ],
    [
      153.275,
      -28.400889,
      770
    ],
    [
      153.274982,
      -28.400987,
      768
    ],
    [
      153.274929,
      -28.401069,
      769
    ],
    [
      153.274882,
      -28.40116,
      768
    ],
    [
      153.274774,
      -28.401195,
      772
    ],
    [
      153.274683,
      -28.401241,
      775
    ],
    [
      153.274578,
      -28.401283,
      778
    ],
    [
      153.274492,
      -28.401349,
      779
    ],
    [
      153.27446,
      -28.401438,
      777
    ],
    [
      153.274383,
      -28.401504,
      779
    ],
    [
      153.274336,
      -28.40159,
      779
    ],
    [
      153.274286,
      -28.401503,
      784
    ],
    [
      153.274268,
      -28.401401,
      789
    ],
    [
      153.274347,
      -28.40134,
      787
    ],
    [
      153.274394,
      -28.401248,
      788
    ],
    [
      153.274438,
      -28.401163,
      789
    ],
    [
      153.274426,
      -28.401068,
      794
    ],
    [
      153.274455,
      -28.400964,
      797
    ],
    [
      153.274492,
      -28.400865,
      799
    ],
    [
      153.274529,
      -28.400777,
      799
    ],
    [
      153.274529,
      -28.400679,
      802
    ],
    [
      153.274534,
      -28.400583,
      804
    ],
    [
      153.27454,
      -28.400482,
      806
    ],
    [
      153.274561,
      -28.400388,
      808
    ],
    [
      153.274625,
      -28.400314,
      807
    ],
    [
      153.274706,
      -28.400226,
      805
    ],
    [
      153.274616,
      -28.400167,
      812
    ],
    [
      153.27453,
      -28.400115,
      819
    ],
    [
      153.274589,
      -28.400035,
      817
    ],
    [
      153.274676,
      -28.399987,
      812
    ],
    [
      153.274737,
      -28.399901,
      810
    ],
    [
      153.274745,
      -28.39981,
      812
    ],
    [
      153.274667,
      -28.399882,
      815
    ],
    [
      153.274568,
      -28.399939,
      821
    ],
    [
      153.274474,
      -28.399991,
      826
    ],
    [
      153.274392,
      -28.400047,
      829
    ],
    [
      153.274326,
      -28.400125,
      829
    ],
    [
      153.274246,
      -28.400189,
      830
    ],
    [
      153.274167,
      -28.400257,
      831
    ],
    [
      153.274121,
      -28.400344,
      830
    ],
    [
      153.274025,
      -28.400403,
      833
    ],
    [
      153.273956,
      -28.400477,
      834
    ],
    [
      153.273881,
      -28.400566,
      835
    ],
    [
      153.27383,
      -28.400645,
      835
    ],
    [
      153.273764,
      -28.400719,
      836
    ],
    [
      153.273661,
      -28.40076,
      840
    ],
    [
      153.273582,
      -28.400825,
      843
    ],
    [
      153.273515,
      -28.400924,
      843
    ],
    [
      153.273394,
      -28.400963,
      848
    ],
    [
      153.273326,
      -28.401032,
      850
    ],
    [
      153.273234,
      -28.40109,
      853
    ],
    [
      153.273127,
      -28.401073,
      859
    ],
    [
      153.273046,
      -28.401145,
      861
    ],
    [
      153.273021,
      -28.401243,
      859
    ],
    [
      153.273009,
      -28.401337,
      856
    ],
    [
      153.272988,
      -28.401444,
      853
    ],
    [
      153.272916,
      -28.401521,
      853
    ],
    [
      153.272852,
      -28.401596,
      853
    ],
    [
      153.272789,
      -28.401691,
      851
    ],
    [
      153.272738,
      -28.401778,
      849
    ],
    [
      153.272646,
      -28.401825,
      850
    ],
    [
      153.272562,
      -28.401889,
      850
    ],
    [
      153.272454,
      -28.40193,
      852
    ],
    [
      153.272353,
      -28.40191,
      857
    ],
    [
      153.272256,
      -28.40187,
      863
    ],
    [
      153.272152,
      -28.401841,
      869
    ],
    [
      153.272067,
      -28.401791,
      874
    ],
    [
      153.272136,
      -28.4017,
      875
    ],
    [
      153.27223,
      -28.401652,
      873
    ],
    [
      153.272335,
      -28.401686,
      868
    ],
    [
      153.272441,
      -28.401655,
      866
    ],
    [
      153.272432,
      -28.401556,
      870
    ],
    [
      153.272453,
      -28.401451,
      874
    ],
    [
      153.272472,
      -28.401353,
      877
    ],
    [
      153.272451,
      -28.401257,
      882
    ],
    [
      153.272431,
      -28.401168,
      886
    ],
    [
      153.272434,
      -28.401066,
      889
    ],
    [
      153.272413,
      -28.400959,
      893
    ],
    [
      153.27243,
      -28.400865,
      896
    ],
    [
      153.2725,
      -28.400788,
      895
    ],
    [
      153.272556,
      -28.400696,
      895
    ],
    [
      153.272571,
      -28.400601,
      897
    ],
    [
      153.272598,
      -28.400495,
      899
    ],
    [
      153.272653,
      -28.400408,
      899
    ],
    [
      153.272704,
      -28.400317,
      900
    ],
    [
      153.272752,
      -28.400232,
      901
    ],
    [
      153.272789,
      -28.400142,
      903
    ],
    [
      153.272843,
      -28.400055,
      905
    ],
    [
      153.272919,
      -28.399984,
      905
    ],
    [
      153.272949,
      -28.399891,
      907
    ],
    [
      153.27297,
      -28.399791,
      909
    ],
    [
      153.273018,
      -28.399711,
      909
    ],
    [
      153.273006,
      -28.399619,
      914
    ],
    [
      153.273068,
      -28.399545,
      913
    ],
    [
      153.273081,
      -28.399453,
      916
    ],
    [
      153.273121,
      -28.399368,
      918
    ],
    [
      153.273193,
      -28.399302,
      917
    ],
    [
      153.273213,
      -28.399208,
      921
    ],
    [
      153.273272,
      -28.399119,
      922
    ],
    [
      153.273305,
      -28.399022,
      924
    ],
    [
      153.273344,
      -28.398932,
      925
    ],
    [
      153.273417,
      -28.398867,
      923
    ],
    [
      153.273336,
      -28.398934,
      925
    ],
    [
      153.273273,
      -28.399006,
      926
    ],
    [
      153.273157,
      -28.398993,
      934
    ],
    [
      153.273069,
      -28.399057,
      937
    ],
    [
      153.273013,
      -28.399137,
      936
    ],
    [
      153.272934,
      -28.399213,
      938
    ],
    [
      153.272853,
      -28.399286,
      939
    ],
    [
      153.272768,
      -28.39935,
      940
    ],
    [
      153.272685,
      -28.399412,
      942
    ],
    [
      153.272618,
      -28.399483,
      943
    ],
    [
      153.272584,
      -28.399568,
      941
    ],
    [
      153.272536,
      -28.399668,
      939
    ],
    [
      153.272498,
      -28.399579,
      946
    ],
    [
      153.272529,
      -28.399486,
      949
    ],
    [
      153.272576,
      -28.399399,
      952
    ],
    [
      153.272552,
      -28.399305,
      960
    ],
    [
      153.272448,
      -28.399309,
      968
    ],
    [
      153.272378,
      -28.399389,
      967
    ],
    [
      153.272381,
      -28.39948,
      960
    ],
    [
      153.272302,
      -28.399544,
      961
    ],
    [
      153.272311,
      -28.399453,
      966
    ],
    [
      153.272308,
      -28.399362,
      974
    ],
    [
      153.27223,
      -28.399425,
      974
    ],
    [
      153.272163,
      -28.399513,
      973
    ],
    [
      153.272134,
      -28.399608,
      969
    ],
    [
      153.272062,
      -28.399523,
      981
    ],
    [
      153.271941,
      -28.399549,
      990
    ],
    [
      153.271874,
      -28.399624,
      989
    ],
    [
      153.271777,
      -28.399651,
      995
    ],
    [
      153.27172,
      -28.399743,
      991
    ],
    [
      153.27163,
      -28.399818,
      992
    ],
    [
      153.271566,
      -28.399893,
      991
    ],
    [
      153.271477,
      -28.399943,
      993
    ],
    [
      153.271369,
      -28.399974,
      998
    ],
    [
      153.271314,
      -28.400074,
      995
    ],
    [
      153.27119,
      -28.400072,
      1004
    ],
    [
      153.271105,
      -28.400131,
      1005
    ],
    [
      153.271016,
      -28.400186,
      1005
    ],
    [
      153.27093,
      -28.400239,
      1006
    ],
    [
      153.270867,
      -28.400311,
      1005
    ],
    [
      153.27077,
      -28.400371,
      1003
    ],
    [
      153.270666,
      -28.400383,
      1003
    ],
    [
      153.270549,
      -28.400405,
      1002
    ],
    [
      153.270449,
      -28.400449,
      998
    ],
    [
      153.270374,
      -28.400522,
      992
    ],
    [
      153.270289,
      -28.400473,
      994
    ],
    [
      153.270197,
      -28.400417,
      996
    ],
    [
      153.27012,
      -28.400351,
      999
    ],
    [
      153.270085,
      -28.40026,
      1003
    ],
    [
      153.27016,
      -28.400195,
      1007
    ],
    [
      153.270114,
      -28.400108,
      1009
    ],
    [
      153.27005,
      -28.400034,
      1009
    ],
    [
      153.270151,
      -28.400012,
      1013
    ],
    [
      153.270204,
      -28.400104,
      1011
    ],
    [
      153.270251,
      -28.400187,
      1009
    ],
    [
      153.270351,
      -28.400229,
      1009
    ],
    [
      153.270435,
      -28.400167,
      1014
    ],
    [
      153.27049,
      -28.400088,
      1018
    ],
    [
      153.270553,
      -28.400013,
      1023
    ],
    [
      153.27058,
      -28.399918,
      1027
    ],
    [
      153.270625,
      -28.399829,
      1031
    ],
    [
      153.270647,
      -28.399714,
      1035
    ],
    [
      153.270726,
      -28.399649,
      1039
    ],
    [
      153.270774,
      -28.399561,
      1043
    ],
    [
      153.270883,
      -28.399511,
      1047
    ],
    [
      153.270951,
      -28.399444,
      1051
    ],
    [
      153.271011,
      -28.399364,
      1055
    ],
    [
      153.271103,
      -28.399308,
      1059
    ],
    [
      153.271132,
      -28.399216,
      1063
    ],
    [
      153.271021,
      -28.399238,
      1061
    ],
    [
      153.270925,
      -28.399283,
      1057
    ],
    [
      153.270821,
      -28.399265,
      1055
    ],
    [
      153.270804,
      -28.399174,
      1058
    ],
    [
      153.270847,
      -28.399085,
      1061
    ],
    [
      153.270914,
      -28.399,
      1064
    ],
    [
      153.270987,
      -28.398919,
      1069
    ],
    [
      153.271038,
      -28.398835,
      1074
    ],
    [
      153.271154,
      -28.398819,
      1080
    ],
    [
      153.271249,
      -28.39877,
      1086
    ],
    [
      153.271328,
      -28.398701,
      1093
    ],
    [
      153.271405,
      -28.398635,
      1099
    ],
    [
      153.271384,
      -28.398538,
      1106
    ],
    [
      153.271438,
      -28.398445,
      1114
    ],
    [
      153.271496,
      -28.398362,
      1121
    ],
    [
      153.271517,
      -28.398274,
      1120
    ],
    [
      153.271486,
      -28.39818,
      1114
    ],
    [
      153.271501,
      -28.398087,
      1109
    ],
    [
      153.27152,
      -28.397993,
      1101
    ],
    [
      153.271541,
      -28.397902,
      1089
    ],
    [
      153.271579,
      -28.397988,
      1105
    ],
    [
      153.271543,
      -28.398076,
      1113
    ],
    [
      153.271524,
      -28.398165,
      1115
    ],
    [
      153.27151,
      -28.398254,
      1119
    ],
    [
      153.271475,
      -28.398353,
      1121
    ],
    [
      153.271419,
      -28.398441,
      1114
    ],
    [
      153.271413,
      -28.39854,
      1107
    ],
    [
      153.271376,
      -28.398633,
      1099
    ],
    [
      153.271304,
      -28.398712,
      1091
    ],
    [
      153.271233,
      -28.398781,
      1085
    ],
    [
      153.271138,
      -28.398834,
      1079
    ],
    [
      153.271035,
      -28.39884,
      1074
    ],
    [
      153.270994,
      -28.398928,
      1069
    ],
    [
      153.270947,
      -28.39902,
      1065
    ],
    [
      153.270867,
      -28.399079,
      1061
    ],
    [
      153.270829,
      -28.399165,
      1059
    ],
    [
      153.270857,
      -28.399251,
      1057
    ],
    [
      153.27096,
      -28.399261,
      1058
    ],
    [
      153.271059,
      -28.399231,
      1062
    ],
    [
      153.271158,
      -28.399197,
      1064
    ],
    [
      153.271173,
      -28.399288,
      1058
    ],
    [
      153.271129,
      -28.39937,
      1055
    ],
    [
      153.27108,
      -28.399452,
      1051
    ],
    [
      153.271016,
      -28.399528,
      1047
    ],
    [
      153.27094,
      -28.399591,
      1043
    ],
    [
      153.270855,
      -28.399642,
      1041
    ],
    [
      153.270784,
      -28.399712,
      1038
    ],
    [
      153.27072,
      -28.399792,
      1033
    ],
    [
      153.270729,
      -28.399895,
      1029
    ],
    [
      153.270684,
      -28.399985,
      1025
    ],
    [
      153.270675,
      -28.400087,
      1020
    ],
    [
      153.270608,
      -28.400155,
      1017
    ],
    [
      153.270491,
      -28.400193,
      1014
    ],
    [
      153.270387,
      -28.400237,
      1010
    ],
    [
      153.270285,
      -28.400211,
      1009
    ],
    [
      153.270203,
      -28.400142,
      1010
    ],
    [
      153.270143,
      -28.400057,
      1011
    ],
    [
      153.270108,
      -28.400164,
      1007
    ],
    [
      153.270092,
      -28.400264,
      1003
    ],
    [
      153.270138,
      -28.400345,
      999
    ],
    [
      153.270207,
      -28.400414,
      996
    ],
    [
      153.270309,
      -28.40048,
      994
    ],
    [
      153.270408,
      -28.400459,
      997
    ],
    [
      153.270514,
      -28.400419,
      1001
    ],
    [
      153.270621,
      -28.40044,
      999
    ],
    [
      153.270728,
      -28.400421,
      1000
    ],
    [
      153.270815,
      -28.400369,
      1003
    ],
    [
      153.270934,
      -28.400304,
      1001
    ],
    [
      153.271025,
      -28.400248,
      1000
    ],
    [
      153.271102,
      -28.400188,
      1001
    ],
    [
      153.271206,
      -28.400131,
      998
    ],
    [
      153.271288,
      -28.40006,
      998
    ],
    [
      153.271382,
      -28.400009,
      994
    ],
    [
      153.271496,
      -28.399964,
      990
    ],
    [
      153.271606,
      -28.399974,
      983
    ],
    [
      153.271707,
      -28.399937,
      979
    ],
    [
      153.271743,
      -28.399823,
      984
    ],
    [
      153.27179,
      -28.399743,
      986
    ],
    [
      153.2719,
      -28.399706,
      980
    ],
    [
      153.272008,
      -28.399664,
      975
    ],
    [
      153.272091,
      -28.399598,
      973
    ],
    [
      153.272199,
      -28.399571,
      966
    ],
    [
      153.272241,
      -28.399481,
      969
    ],
    [
      153.272294,
      -28.399565,
      960
    ],
    [
      153.272196,
      -28.399671,
      959
    ],
    [
      153.272315,
      -28.399636,
      954
    ],
    [
      153.272386,
      -28.399554,
      955
    ],
    [
      153.272437,
      -28.399459,
      957
    ],
    [
      153.272497,
      -28.399386,
      959
    ],
    [
      153.272591,
      -28.399325,
      956
    ],
    [
      153.272557,
      -28.399435,
      950
    ],
    [
      153.272539,
      -28.399528,
      946
    ],
    [
      153.272533,
      -28.399621,
      942
    ],
    [
      153.272633,
      -28.399588,
      937
    ],
    [
      153.272686,
      -28.399505,
      937
    ],
    [
      153.272723,
      -28.399419,
      939
    ],
    [
      153.272786,
      -28.399343,
      939
    ],
    [
      153.272857,
      -28.399278,
      939
    ],
    [
      153.272946,
      -28.399206,
      937
    ],
    [
      153.273043,
      -28.399131,
      935
    ],
    [
      153.273107,
      -28.399036,
      935
    ],
    [
      153.273215,
      -28.399002,
      930
    ],
    [
      153.273309,
      -28.398946,
      926
    ],
    [
      153.273408,
      -28.398899,
      922
    ],
    [
      153.273493,
      -28.398847,
      919
    ],
    [
      153.273503,
      -28.398938,
      915
    ],
    [
      153.273455,
      -28.39902,
      914
    ],
    [
      153.273365,
      -28.399103,
      916
    ],
    [
      153.273302,
      -28.399187,
      917
    ],
    [
      153.27324,
      -28.399272,
      916
    ],
    [
      153.273217,
      -28.399361,
      912
    ],
    [
      153.273128,
      -28.399426,
      914
    ],
    [
      153.2731,
      -28.399543,
      911
    ],
    [
      153.273073,
      -28.399642,
      909
    ],
    [
      153.273009,
      -28.399735,
      909
    ],
    [
      153.272996,
      -28.399837,
      906
    ],
    [
      153.272977,
      -28.399947,
      904
    ],
    [
      153.272928,
      -28.400037,
      902
    ],
    [
      153.272841,
      -28.400133,
      901
    ],
    [
      153.27277,
      -28.400248,
      899
    ],
    [
      153.272711,
      -28.40034,
      899
    ],
    [
      153.272664,
      -28.400454,
      897
    ],
    [
      153.272664,
      -28.400557,
      894
    ],
    [
      153.272674,
      -28.400652,
      891
    ],
    [
      153.272583,
      -28.400722,
      893
    ],
    [
      153.272518,
      -28.400808,
      894
    ],
    [
      153.272447,
      -28.400891,
      894
    ],
    [
      153.2725,
      -28.400993,
      889
    ],
    [
      153.272515,
      -28.401099,
      885
    ],
    [
      153.272464,
      -28.401202,
      883
    ],
    [
      153.272451,
      -28.401299,
      880
    ],
    [
      153.272468,
      -28.401392,
      876
    ],
    [
      153.272527,
      -28.401471,
      870
    ],
    [
      153.272516,
      -28.401573,
      866
    ],
    [
      153.272438,
      -28.401647,
      866
    ],
    [
      153.272346,
      -28.401699,
      867
    ],
    [
      153.272233,
      -28.401683,
      872
    ],
    [
      153.272118,
      -28.401739,
      874
    ],
    [
      153.272057,
      -28.401821,
      874
    ],
    [
      153.272156,
      -28.401853,
      868
    ],
    [
      153.27228,
      -28.401882,
      861
    ],
    [
      153.272381,
      -28.401917,
      856
    ],
    [
      153.272491,
      -28.401925,
      851
    ],
    [
      153.272595,
      -28.401901,
      848
    ],
    [
      153.27272,
      -28.401819,
      848
    ],
    [
      153.2728,
      -28.40173,
      849
    ],
    [
      153.272876,
      -28.401652,
      850
    ],
    [
      153.272923,
      -28.401555,
      852
    ],
    [
      153.272976,
      -28.40147,
      853
    ],
    [
      153.27305,
      -28.40139,
      852
    ],
    [
      153.273061,
      -28.401282,
      856
    ],
    [
      153.273084,
      -28.401186,
      858
    ],
    [
      153.273211,
      -28.401114,
      854
    ],
    [
      153.273317,
      -28.401036,
      850
    ],
    [
      153.273414,
      -28.400996,
      846
    ],
    [
      153.273496,
      -28.400922,
      844
    ],
    [
      153.273612,
      -28.400888,
      839
    ],
    [
      153.273718,
      -28.400843,
      834
    ],
    [
      153.273791,
      -28.400744,
      833
    ],
    [
      153.273851,
      -28.400665,
      833
    ],
    [
      153.273916,
      -28.400593,
      832
    ],
    [
      153.273951,
      -28.400498,
      834
    ],
    [
      153.274056,
      -28.400429,
      831
    ],
    [
      153.274098,
      -28.400322,
      832
    ],
    [
      153.274199,
      -28.400278,
      829
    ],
    [
      153.274289,
      -28.400215,
      827
    ],
    [
      153.274394,
      -28.400176,
      824
    ],
    [
      153.274493,
      -28.400145,
      820
    ],
    [
      153.274566,
      -28.400069,
      818
    ],
    [
      153.274661,
      -28.399998,
      813
    ],
    [
      153.274766,
      -28.399955,
      807
    ],
    [
      153.274876,
      -28.399897,
      801
    ],
    [
      153.274821,
      -28.399989,
      802
    ],
    [
      153.274708,
      -28.400072,
      808
    ],
    [
      153.274622,
      -28.400122,
      813
    ],
    [
      153.274567,
      -28.40022,
      813
    ],
    [
      153.274683,
      -28.40019,
      807
    ],
    [
      153.274787,
      -28.400164,
      801
    ],
    [
      153.274812,
      -28.400277,
      797
    ],
    [
      153.274711,
      -28.400389,
      800
    ],
    [
      153.274616,
      -28.400424,
      804
    ],
    [
      153.274607,
      -28.400521,
      802
    ],
    [
      153.27462,
      -28.400617,
      798
    ],
    [
      153.274607,
      -28.400707,
      797
    ],
    [
      153.2746,
      -28.400833,
      793
    ],
    [
      153.274557,
      -28.400928,
      793
    ],
    [
      153.274483,
      -28.401014,
      793
    ],
    [
      153.274447,
      -28.40112,
      790
    ],
    [
      153.274445,
      -28.401214,
      787
    ],
    [
      153.274412,
      -28.401321,
      784
    ],
    [
      153.274339,
      -28.401392,
      785
    ],
    [
      153.274266,
      -28.401462,
      787
    ],
    [
      153.274238,
      -28.401561,
      785
    ],
    [
      153.274363,
      -28.401605,
      777
    ],
    [
      153.274464,
      -28.401582,
      772
    ],
    [
      153.274548,
      -28.401518,
      770
    ],
    [
      153.274651,
      -28.401459,
      767
    ],
    [
      153.274741,
      -28.401396,
      766
    ],
    [
      153.274853,
      -28.401341,
      762
    ],
    [
      153.274892,
      -28.401238,
      764
    ],
    [
      153.27491,
      -28.401147,
      767
    ],
    [
      153.274956,
      -28.401063,
      767
    ],
    [
      153.274987,
      -28.400977,
      768
    ],
    [
      153.274999,
      -28.400883,
      770
    ],
    [
      153.275057,
      -28.400804,
      768
    ],
    [
      153.275164,
      -28.400776,
      762
    ],
    [
      153.275269,
      -28.400745,
      756
    ],
    [
      153.275361,
      -28.400689,
      754
    ],
    [
      153.275425,
      -28.400617,
      753
    ],
    [
      153.275507,
      -28.400541,
      752
    ],
    [
      153.275581,
      -28.400473,
      750
    ],
    [
      153.275664,
      -28.400417,
      746
    ],
    [
      153.275573,
      -28.400464,
      750
    ],
    [
      153.27556,
      -28.400562,
      750
    ],
    [
      153.275523,
      -28.400649,
      748
    ],
    [
      153.275504,
      -28.400739,
      746
    ],
    [
      153.275456,
      -28.400831,
      746
    ],
    [
      153.275404,
      -28.400909,
      746
    ],
    [
      153.275413,
      -28.40105,
      740
    ],
    [
      153.275485,
      -28.401126,
      734
    ],
    [
      153.275553,
      -28.401057,
      733
    ],
    [
      153.275649,
      -28.401014,
      730
    ],
    [
      153.27574,
      -28.400952,
      728
    ],
    [
      153.275764,
      -28.400856,
      730
    ],
    [
      153.275874,
      -28.400782,
      727
    ],
    [
      153.27598,
      -28.400697,
      724
    ],
    [
      153.276106,
      -28.400635,
      719
    ],
    [
      153.276192,
      -28.400572,
      717
    ],
    [
      153.276227,
      -28.400487,
      716
    ],
    [
      153.276224,
      -28.400396,
      716
    ],
    [
      153.276302,
      -28.400466,
      713
    ],
    [
      153.276284,
      -28.400556,
      714
    ],
    [
      153.276225,
      -28.40066,
      714
    ],
    [
      153.276183,
      -28.400755,
      713
    ],
    [
      153.276171,
      -28.400851,
      712
    ],
    [
      153.276151,
      -28.400965,
      709
    ],
    [
      153.276162,
      -28.40106,
      706
    ],
    [
      153.27626,
      -28.401132,
      700
    ],
    [
      153.276304,
      -28.401214,
      695
    ],
    [
      153.276284,
      -28.401307,
      694
    ],
    [
      153.276223,
      -28.401384,
      694
    ],
    [
      153.276112,
      -28.401412,
      697
    ],
    [
      153.27606,
      -28.401492,
      697
    ],
    [
      153.275991,
      -28.401564,
      698
    ],
    [
      153.275921,
      -28.401676,
      698
    ],
    [
      153.275937,
      -28.401765,
      694
    ],
    [
      153.275894,
      -28.401863,
      692
    ],
    [
      153.27582,
      -28.401925,
      693
    ],
    [
      153.275936,
      -28.401964,
      686
    ],
    [
      153.276048,
      -28.401967,
      681
    ],
    [
      153.276156,
      -28.401963,
      676
    ],
    [
      153.276239,
      -28.401908,
      674
    ],
    [
      153.276344,
      -28.401813,
      673
    ],
    [
      153.276433,
      -28.401764,
      671
    ],
    [
      153.276527,
      -28.401719,
      668
    ],
    [
      153.276639,
      -28.401711,
      663
    ],
    [
      153.276744,
      -28.401681,
      661
    ],
    [
      153.276823,
      -28.401616,
      662
    ],
    [
      153.276924,
      -28.401575,
      661
    ],
    [
      153.276966,
      -28.401477,
      663
    ],
    [
      153.277002,
      -28.401388,
      666
    ],
    [
      153.277116,
      -28.401306,
      665
    ],
    [
      153.277205,
      -28.401228,
      664
    ],
    [
      153.2773,
      -28.401187,
      662
    ],
    [
      153.277365,
      -28.4011,
      661
    ],
    [
      153.277488,
      -28.401068,
      657
    ],
    [
      153.277584,
      -28.400997,
      653
    ],
    [
      153.277615,
      -28.400878,
      652
    ],
    [
      153.27765,
      -28.400787,
      650
    ],
    [
      153.277692,
      -28.400677,
      647
    ],
    [
      153.277679,
      -28.400573,
      646
    ],
    [
      153.277653,
      -28.400463,
      647
    ],
    [
      153.277632,
      -28.400364,
      646
    ],
    [
      153.277695,
      -28.40046,
      645
    ],
    [
      153.277792,
      -28.400535,
      640
    ],
    [
      153.277886,
      -28.400609,
      634
    ],
    [
      153.277986,
      -28.400682,
      628
    ],
    [
      153.27805,
      -28.400768,
      625
    ],
    [
      153.278095,
      -28.400857,
      623
    ],
    [
      153.278019,
      -28.400927,
      629
    ],
    [
      153.278028,
      -28.401026,
      629
    ],
    [
      153.27811,
      -28.401085,
      626
    ],
    [
      153.278192,
      -28.401168,
      623
    ],
    [
      153.278263,
      -28.401251,
      620
    ],
    [
      153.278329,
      -28.401359,
      618
    ],
    [
      153.278383,
      -28.401455,
      617
    ],
    [
      153.278446,
      -28.401543,
      616
    ],
    [
      153.278488,
      -28.401634,
      616
    ],
    [
      153.278574,
      -28.401711,
      614
    ],
    [
      153.278634,
      -28.401796,
      613
    ],
    [
      153.278716,
      -28.401897,
      613
    ],
    [
      153.278861,
      -28.401865,
      611
    ],
    [
      153.27896,
      -28.401806,
      609
    ],
    [
      153.279007,
      -28.401689,
      607
    ],
    [
      153.278958,
      -28.401579,
      607
    ],
    [
      153.278897,
      -28.401492,
      608
    ],
    [
      153.278823,
      -28.401404,
      608
    ],
    [
      153.278759,
      -28.401297,
      608
    ],
    [
      153.278729,
      -28.401162,
      606
    ],
    [
      153.278726,
      -28.401065,
      604
    ],
    [
      153.278674,
      -28.400973,
      602
    ],
    [
      153.278624,
      -28.400879,
      602
    ],
    [
      153.278578,
      -28.400784,
      600
    ],
    [
      153.278647,
      -28.400693,
      594
    ],
    [
      153.278641,
      -28.400593,
      590
    ],
    [
      153.278635,
      -28.400498,
      588
    ],
    [
      153.278752,
      -28.400529,
      583
    ],
    [
      153.278858,
      -28.400578,
      579
    ],
    [
      153.27894,
      -28.400663,
      579
    ],
    [
      153.27891,
      -28.400753,
      584
    ],
    [
      153.278938,
      -28.400865,
      587
    ],
    [
      153.279012,
      -28.400937,
      586
    ],
    [
      153.279095,
      -28.400996,
      585
    ],
    [
      153.279238,
      -28.40105,
      581
    ],
    [
      153.27936,
      -28.40108,
      577
    ],
    [
      153.279463,
      -28.401115,
      574
    ],
    [
      153.279371,
      -28.40107,
      576
    ],
    [
      153.279469,
      -28.401044,
      571
    ],
    [
      153.279589,
      -28.401031,
      567
    ],
    [
      153.279738,
      -28.401068,
      563
    ],
    [
      153.279846,
      -28.40106,
      561
    ],
    [
      153.279903,
      -28.400983,
      557
    ],
    [
      153.280013,
      -28.400961,
      554
    ],
    [
      153.28015,
      -28.401023,
      554
    ],
    [
      153.280246,
      -28.40106,
      554
    ],
    [
      153.280312,
      -28.401128,
      555
    ],
    [
      153.280352,
      -28.401215,
      556
    ],
    [
      153.28036,
      -28.401306,
      559
    ],
    [
      153.280474,
      -28.401354,
      557
    ],
    [
      153.280584,
      -28.401427,
      556
    ],
    [
      153.280704,
      -28.401535,
      559
    ],
    [
      153.280758,
      -28.401626,
      562
    ],
    [
      153.280856,
      -28.401555,
      559
    ],
    [
      153.280878,
      -28.401449,
      556
    ],
    [
      153.280938,
      -28.401359,
      554
    ],
    [
      153.280989,
      -28.401261,
      552
    ],
    [
      153.281012,
      -28.401159,
      549
    ],
    [
      153.281054,
      -28.401065,
      546
    ],
    [
      153.28115,
      -28.40098,
      542
    ],
    [
      153.2812,
      -28.400859,
      535
    ],
    [
      153.281283,
      -28.400784,
      531
    ],
    [
      153.281375,
      -28.400734,
      527
    ],
    [
      153.281491,
      -28.400706,
      525
    ],
    [
      153.28162,
      -28.400698,
      523
    ],
    [
      153.28172,
      -28.400676,
      521
    ],
    [
      153.281828,
      -28.400746,
      523
    ],
    [
      153.281925,
      -28.400786,
      524
    ],
    [
      153.282073,
      -28.400845,
      528
    ],
    [
      153.282182,
      -28.400795,
      526
    ],
    [
      153.28223,
      -28.400692,
      520
    ],
    [
      153.282301,
      -28.400606,
      514
    ],
    [
      153.282377,
      -28.400543,
      510
    ],
    [
      153.282381,
      -28.400426,
      504
    ],
    [
      153.282414,
      -28.400336,
      499
    ],
    [
      153.282496,
      -28.400269,
      494
    ],
    [
      153.282625,
      -28.400191,
      491
    ],
    [
      153.282698,
      -28.400119,
      489
    ],
    [
      153.282798,
      -28.400062,
      487
    ],
    [
      153.282912,
      -28.40005,
      486
    ],
    [
      153.283008,
      -28.400009,
      484
    ],
    [
      153.283075,
      -28.399903,
      482
    ],
    [
      153.283111,
      -28.399815,
      480
    ],
    [
      153.283177,
      -28.399735,
      478
    ],
    [
      153.283254,
      -28.399669,
      477
    ],
    [
      153.283357,
      -28.399656,
      477
    ],
    [
      153.283491,
      -28.399648,
      478
    ],
    [
      153.28359,
      -28.399619,
      478
    ],
    [
      153.283719,
      -28.399603,
      478
    ],
    [
      153.283814,
      -28.39957,
      478
    ],
    [
      153.283902,
      -28.399523,
      478
    ],
    [
      153.283989,
      -28.399477,
      476
    ],
    [
      153.284093,
      -28.399418,
      473
    ],
    [
      153.28417,
      -28.399358,
      470
    ],
    [
      153.284256,
      -28.399303,
      467
    ],
    [
      153.284304,
      -28.399212,
      464
    ],
    [
      153.284289,
      -28.399105,
      460
    ],
    [
      153.284297,
      -28.398992,
      456
    ],
    [
      153.284351,
      -28.398914,
      454
    ],
    [
      153.284255,
      -28.398864,
      452
    ],
    [
      153.284276,
      -28.398761,
      450
    ],
    [
      153.284192,
      -28.398682,
      448
    ],
    [
      153.284248,
      -28.398579,
      445
    ],
    [
      153.284281,
      -28.398493,
      443
    ],
    [
      153.284345,
      -28.398343,
      438
    ],
    [
      153.284445,
      -28.398281,
      435
    ],
    [
      153.284633,
      -28.398254,
      431
    ]
  ],
  "distanceKm": 8.6,
  "elevationMin": 431,
  "elevationMax": 1121,
  "error": 4.7
}
